confit/__init__.py
confit/version.py
figurator/__init__.py
figurator/version.py
figurator-0.0.0.dist-info/METADATA
figurator-0.0.0.dist-info/WHEEL
figurator-0.0.0.dist-info/top_level.txt
figurator-0.0.0.dist-info/RECORD
